{
	"Ads": [{
		"select_main_ads": "ADMOB",
		"select_backup_ads": "APPLOVIN-M",
		"main_ads_banner": "ca-app-pub-3940256099942544/6300978111x",
		"main_ads_intertitial": "ca-app-pub-3940256099942544/1033173712x",
		"backup_ads_banner": "db4d5e8718b97d78",
		"backup_ads_intertitial": "518cd97722c60b52",
		"interval_intertitial": 5,
		"initialize_sdk": "107355779",
		"initialize_sdk_backup_ads": "",
		"high_paying_keyword_1": "",
		"high_paying_keyword_2": "",
		"high_paying_keyword_3": "",
		"high_paying_keyword_4": "",
		"high_paying_keyword_5": "",
		"status_app": "0",
		"link_redirect": "https://"
	}],
	"Categories": [{
		"id": 1,
		"name_category": "Charlie Puth",
		"image": "file:///android_asset/image/charlieputh.jpg"
	}],
	"Data": [{
			"id": 1,
			"name_category": "Charlie Puth",
			"title": "Left And Right (feat. Jung Kook of BTS)",
			"image": "file:///android_asset/image/charlieputh.jpg",
			"link_mp3": "mp3/Left_And_Right.mp3",
			"duration": "159",
			"lyrics": ""
		},

		{
			"id": 2,
			"name_category": "Charlie Puth",
			"title": "Light Switch",
			"image": "file:///android_asset/image/charlieputh.jpg",
			"link_mp3": "mp3/Light_Switch.mp3",
			"duration": "204",
			"lyrics": ""
		},

		{
			"id": 3,
			"name_category": "Charlie Puth",
			"title": "Attention",
			"image": "file:///android_asset/image/charlieputh.jpg",
			"link_mp3": "mp3/Attention.mp3",
			"duration": "231",
			"lyrics": ""
		},

		{
			"id": 4,
			"name_category": "Charlie Puth",
			"title": "Cheating on You",
			"image": "file:///android_asset/image/charlieputh.jpg",
			"link_mp3": "mp3/Cheating on You.mp3",
			"duration": "201",
			"lyrics": ""
		},

		{
			"id": 5,
			"name_category": "Charlie Puth",
			"title": "Done For Me feat. Kehlani",
			"image": "file:///android_asset/image/charlieputh.jpg",
			"link_mp3": "mp3/Done For Me.mp3",
			"duration": "176",
			"lyrics": ""
		},

		{
			"id": 6,
			"name_category": "Charlie Puth",
			"title": "How Long",
			"image": "file:///android_asset/image/charlieputh.jpg",
			"link_mp3": "mp3/How Long.mp3",
			"duration": "210",
			"lyrics": ""
		},

		{
			"id": 7,
			"name_category": "Charlie Puth",
			"title": "Marvin Gaye ft. Meghan Trainor",
			"image": "file:///android_asset/image/charlieputh.jpg",
			"link_mp3": "mp3/Marvin Gaye.mp3",
			"duration": "209",
			"lyrics": ""
		},

		{
			"id": 8,
			"name_category": "Charlie Puth",
			"title": "One Call Away",
			"image": "file:///android_asset/image/charlieputh.jpg",
			"link_mp3": "mp3/One Call Away.mp3",
			"duration": "241",
			"lyrics": ""
		},

		{
			"id": 9,
			"name_category": "Charlie Puth",
			"title": "That's Hilarious",
			"image": "file:///android_asset/image/charlieputh.jpg",
			"link_mp3": "mp3/That's Hilarious.mp3",
			"duration": "145",
			"lyrics": ""
		},

		{
			"id": 10,
			"name_category": "Charlie Puth",
			"title": "The Way I Am",
			"image": "file:///android_asset/image/charlieputh.jpg",
			"link_mp3": "mp3/The Way I Am.mp3",
			"duration": "185",
			"lyrics": ""
		},

		{
			"id": 11,
			"name_category": "Charlie Puth",
			"title": "We Don't Talk Anymore",
			"image": "file:///android_asset/image/charlieputh.jpg",
			"link_mp3": "mp3/We Don't Talk Anymore.mp3",
			"duration": "230",
			"lyrics": ""
		}
	]
}